behave_restful/__init__.py
behave_restful/_definitions.py
behave_restful/_errors.py
behave_restful/_hooks.py
behave_restful/_schemas.py
behave_restful/_utils.py
behave_restful/about.py
behave_restful/app.py
behave_restful/bolt_behave_restful.py
behave_restful/cli.py
behave_restful/tools.py
behave_restful/xpy.py
behave_restful/_lang_imp/__init__.py
behave_restful/_lang_imp/request_builder.py
behave_restful/_lang_imp/request_invoker.py
behave_restful/_lang_imp/response_validator.py
behave_restful/_project/environment.py
behave_restful/_project/sample.feature
behave_restful/_project/definitions/sample.py
behave_restful/_project/hooks/sample_hook.py
behave_restful/_project/steps/rest_steps.py
behave_restful/lang/__init__.py
behave_restful/lang/_given_steps.py
behave_restful/lang/_then_steps.py
behave_restful/lang/_when_steps.py
behave_restful-0.4.4.dist-info/LICENSE
behave_restful-0.4.4.dist-info/METADATA
behave_restful-0.4.4.dist-info/WHEEL
behave_restful-0.4.4.dist-info/entry_points.txt
behave_restful-0.4.4.dist-info/top_level.txt
behave_restful-0.4.4.dist-info/RECORD
