Metadata-Version: 2.1
Name: behave-restful
Version: 0.4.4
Summary: Implements Gherking language for REST services.
Home-page: https://github.com/behave-restful/behave-restful
Author: Isaac Rodriguez
Author-email: oss.abantos@outlook.com
License: MIT
Keywords: rest bdd behave gherkin test automation testing
Classifier: Development Status :: 1 - Planning
Classifier: Environment :: Console
Classifier: Intended Audience :: Developers
Classifier: License :: OSI Approved :: MIT License
Classifier: Programming Language :: Python
Classifier: Programming Language :: Python :: 3
Classifier: Programming Language :: Python :: 3.7
Classifier: Programming Language :: Python :: 3.8
Classifier: Programming Language :: Python :: 3.9
Classifier: Topic :: Internet :: WWW/HTTP
Classifier: Topic :: Software Development :: Testing :: Acceptance
Classifier: Topic :: Software Development :: Testing :: BDD
License-File: LICENSE
Requires-Dist: assertpy
Requires-Dist: behave
Requires-Dist: jsonpath
Requires-Dist: jsonref
Requires-Dist: jsonschema
Requires-Dist: PyYaml
Requires-Dist: requests
